[
    {
        "release_v_dig": "ae",
        "release_v_rec": "am",
        "primary_name": "CeEndpoint",
        "digitype": "OnSpill",
        "db_purpose": "best",
        "stream": "Triggered",
        "simjob_setup": "/cvmfs/mu2e.opensciencegrid.org/Musings/SimJob/MDC2020am/setup.sh"
    },
    {
        "release_v_dig": "ae",
        "release_v_rec": "am",
        "primary_name": "CeEndpoint",
        "digitype": "OnSpill",
        "db_purpose": "perfect",
        "stream": "Triggered",
        "simjob_setup": "/cvmfs/mu2e.opensciencegrid.org/Musings/SimJob/MDC2020am/setup.sh"
    },
    {
        "release_v_dig": "ae",
        "release_v_rec": "am",
        "primary_name": "CePlusEndpoint",
        "digitype": "OnSpill",
        "db_purpose": "best",
        "stream": "Triggered",
        "simjob_setup": "/cvmfs/mu2e.opensciencegrid.org/Musings/SimJob/MDC2020am/setup.sh"
    },
    {
        "release_v_dig": "ae",
        "release_v_rec": "am",
        "primary_name": "CePlusEndpoint",
        "digitype": "OnSpill",
        "db_purpose": "perfect",
        "stream": "Triggered",
        "simjob_setup": "/cvmfs/mu2e.opensciencegrid.org/Musings/SimJob/MDC2020am/setup.sh"
    },
    {
        "release_v_dig": "ae",
        "release_v_rec": "am",
        "primary_name": "CosmicCORSIKACalibAll",
        "digitype": "OffSpill",
        "db_purpose": "best",
        "stream": "Triggered",
        "simjob_setup": "/cvmfs/mu2e.opensciencegrid.org/Musings/SimJob/MDC2020am/setup.sh"
    },
    {
        "release_v_dig": "ae",
        "release_v_rec": "am",
        "primary_name": "CosmicCORSIKACalibAll",
        "digitype": "OffSpill",
        "db_purpose": "perfect",
        "stream": "Triggered",
        "simjob_setup": "/cvmfs/mu2e.opensciencegrid.org/Musings/SimJob/MDC2020am/setup.sh"
    },
    {
        "release_v_dig": "ae",
        "release_v_rec": "am",
        "primary_name": "CosmicCORSIKACalibAll",
        "digitype": "OnSpill",
        "db_purpose": "best",
        "stream": "Triggered",
        "simjob_setup": "/cvmfs/mu2e.opensciencegrid.org/Musings/SimJob/MDC2020am/setup.sh"
    },
    {
        "release_v_dig": "ae",
        "release_v_rec": "am",
        "primary_name": "CosmicCORSIKACalibAll",
        "digitype": "OnSpill",
        "db_purpose": "perfect",
        "stream": "Triggered",
        "simjob_setup": "/cvmfs/mu2e.opensciencegrid.org/Musings/SimJob/MDC2020am/setup.sh"
    },
    {
        "release_v_dig": "ae",
        "release_v_rec": "am",
        "primary_name": "CosmicCORSIKASignalAll",
        "digitype": "OffSpill",
        "db_purpose": "best",
        "stream": "Triggered",
        "simjob_setup": "/cvmfs/mu2e.opensciencegrid.org/Musings/SimJob/MDC2020am/setup.sh"
    },
    {
        "release_v_dig": "ae",
        "release_v_rec": "am",
        "primary_name": "CosmicCORSIKASignalAll",
        "digitype": "OffSpill",
        "db_purpose": "perfect",
        "stream": "Triggered",
        "simjob_setup": "/cvmfs/mu2e.opensciencegrid.org/Musings/SimJob/MDC2020am/setup.sh"
    },
    {
        "release_v_dig": "ae",
        "release_v_rec": "am",
        "primary_name": "CosmicCORSIKASignalAll",
        "digitype": "OnSpill",
        "db_purpose": "best",
        "stream": "Triggered",
        "simjob_setup": "/cvmfs/mu2e.opensciencegrid.org/Musings/SimJob/MDC2020am/setup.sh"
    },
    {
        "release_v_dig": "ae",
        "release_v_rec": "am",
        "primary_name": "CosmicCORSIKASignalAll",
        "digitype": "OnSpill",
        "db_purpose": "perfect",
        "stream": "Triggered",
        "simjob_setup": "/cvmfs/mu2e.opensciencegrid.org/Musings/SimJob/MDC2020am/setup.sh"
    },
    {
        "release_v_dig": "ae",
        "release_v_rec": "am",
        "primary_name": "CosmicCRYExtractedCat",
        "digitype": "Extracted",
        "db_purpose": "best",
        "stream": "Triggered",
        "simjob_setup": "/cvmfs/mu2e.opensciencegrid.org/Musings/SimJob/MDC2020am/setup.sh"
    }
]
